{
    "folder_name": "ror_cms_2",
    "name": "Clean Blog",
    "template_version": "1.0",
    "cms_version": "1.0",
    "author": "Clean Blog",
    "email": "",
    "url": "http://ironsummitmedia.github.io/startbootstrap-clean-blog/index.html",
    "description": "The template name is Clean Blog. You can see here: http://ironsummitmedia.github.io/startbootstrap-clean-blog/index.html",
    "license": "license",
    "css_files": ["application.css.scss","bootstrap.css","discuss.scss","galleries.scss","landing.scss","page_single.scss","percategory.scss"],
    "js_files": ["application.js","article_single.js","discuss.js","galleries.js","landing.js","page_single.js","percategory.js"],
    "supplements": [
        { "copy_type": "file", "name": "home-bg.jpg", "copy_to": "app/assets/images" },
        { "copy_type": "folder", "name": "fonts", "copy_to": "public" }
    ]
}
